mkdocs_typer/__init__.py
mkdocs_typer/__version__.py
mkdocs_typer/_docs.py
mkdocs_typer/_exceptions.py
mkdocs_typer/_extension.py
mkdocs_typer/_loader.py
mkdocs_typer/_processing.py
mkdocs_typer/py.typed
mkdocs_typer-0.0.3.dist-info/LICENSE
mkdocs_typer-0.0.3.dist-info/METADATA
mkdocs_typer-0.0.3.dist-info/WHEEL
mkdocs_typer-0.0.3.dist-info/entry_points.txt
mkdocs_typer-0.0.3.dist-info/top_level.txt
mkdocs_typer-0.0.3.dist-info/RECORD
