Metadata-Version: 2.1
Name: mkdocs-typer
Version: 0.0.3
Summary: An MkDocs extension to generate documentation for Typer command line applications
Home-page: https://github.com/bruce-szalwinski/mkdocs-typer
Author: Bruce Szalwinski
Author-email: bruce.szalwinski@gmail.com
License: Apache
Keywords: mkdocs typer
Platform: UNKNOWN
Classifier: Development Status :: 4 - Beta
Classifier: Intended Audience :: Developers
Classifier: Operating System :: OS Independent
Classifier: Programming Language :: Python :: 3
Classifier: Programming Language :: Python :: 3.7
Classifier: Programming Language :: Python :: 3.8
Classifier: Programming Language :: Python :: 3.9
Classifier: Programming Language :: Python :: 3.10
Requires-Python: >=3.7
Requires-Dist: typer (==0.*)
Requires-Dist: markdown (==3.*)
